<?xml version="1.0" encoding="utf-8" ?>
<maiet>
    <SETITEM id="63001" name="앤틱 천 세트" itemid1="63001" itemid2="63002" itemid3="63004" itemid4="63005" />
    <SETITEM id="63011" name="앤틱 가죽 세트" itemid1="63011" itemid2="63012" itemid3="63013" itemid4="63014" itemid5="63015" />
    <SETITEM id="63021" name="알스테어 세트" itemid1="63021" itemid2="63022" itemid3="63024" itemid4="63025" />
    <SETITEM id="63031" name="모험가 세트" itemid1="63031" itemid2="63032" itemid3="63033" itemid4="63034" itemid5="63035" />
    <SETITEM id="63041" name="제사장 세트" itemid1="63041" itemid2="63042" itemid3="63044" itemid4="63045" buffid2="6000000" buffid3="6000001" buffid4="6000002" />
    <SETITEM id="63051" name="해적 세트" itemid1="63051" itemid2="63052" itemid3="63053" itemid4="63054" itemid5="63055" buffid2="6000010" buffid3="6000011" buffid4="6000012" buffid5="6000013" />
    <SETITEM id="60813100" name="말루스 천 세트" itemid1="60813100" itemid2="60813200" itemid3="60813400" itemid4="60813500" />
    <SETITEM id="60813600" name="말루스 가죽 세트" itemid1="60813600" itemid2="60813700" itemid3="60813800" itemid4="60813900" itemid5="60814000" />
    <SETITEM id="60814100" name="말루스 사슬 세트" itemid1="60814100" itemid2="60814200" itemid3="60814300" itemid4="60814400" itemid5="60814500" />
    <SETITEM id="60823100" name="레나스 사제 세트" itemid1="60823100" itemid2="60823200" itemid3="60823300" itemid4="60823400" itemid5="60823500" />
    <SETITEM id="60823600" name="경화 가죽 세트" itemid1="60823600" itemid2="60823700" itemid3="60823800" itemid4="60823900" itemid5="60824000" />
    <SETITEM id="60824100" name="큐프럼 비늘 세트" itemid1="60824100" itemid2="60824200" itemid3="60824300" itemid4="60824400" itemid5="60824500" />
    <SETITEM id="60933100" name="비전 세트" itemid1="60933100" itemid2="60933200" itemid3="60933400" itemid4="60933500" buffid2="6000020" buffid3="6000021" buffid4="6000022" />
    <SETITEM id="60933600" name="척후의 가죽 세트" itemid1="60933600" itemid2="60933700" itemid3="60933800" itemid4="60933900" itemid5="60934000" buffid2="6000030" buffid3="6000031" buffid4="6000032" buffid5="6000033" />
    <SETITEM id="60934100" name="자유의 사슬 세트" itemid1="60934100" itemid2="60934200" itemid3="60934300" itemid4="60934400" itemid5="60934500" buffid2="6000040" buffid3="6000041" buffid4="6000042" buffid5="6000043" />
    <SETITEM id="61213100" name="임벨릭 천 세트" itemid1="61213100" itemid2="61213200" itemid3="61213400" itemid4="61213500" />
    <SETITEM id="61213600" name="임벨릭 가죽 세트" itemid1="61213600" itemid2="61213700" itemid3="61213800" itemid4="61213900" itemid5="61214000" />
    <SETITEM id="61214100" name="임벨릭 사슬 세트" itemid1="61214100" itemid2="61214200" itemid3="61214300" itemid4="61214400" itemid5="61214500" />
    <SETITEM id="61223100" name="해군 제복 세트" itemid1="61223100" itemid2="61223200" itemid3="61223300" itemid4="61223400" itemid5="61223500" />
    <SETITEM id="61223600" name="탐험가 세트" itemid1="61223600" itemid2="61223700" itemid3="61223800" itemid4="61223900" itemid5="61224000" />
    <SETITEM id="61224100" name="위병 세트" itemid1="61224100" itemid2="61224200" itemid3="61224300" itemid4="61224400" itemid5="61224500" />
    <SETITEM id="61333100" name="기사생도 세트" itemid1="61333100" itemid2="61333200" itemid3="61333400" itemid4="61333500" buffid2="6000050" buffid3="6000051" buffid4="6000052" />
    <SETITEM id="61333600" name="전위 세트" itemid1="61333600" itemid2="61333700" itemid3="61333900" itemid4="61334000" buffid2="6000060" buffid3="6000061" buffid4="6000062" />
    <SETITEM id="61334100" name="용병 세트" itemid1="61334100" itemid2="61334200" itemid3="61334300" itemid4="61334400" itemid5="61334500" buffid2="6000070" buffid3="6000071" buffid4="6000072" buffid5="6000073" />
    <SETITEM id="61513100" name="시그넘 천 세트" itemid1="61513100" itemid2="61513200" itemid3="61513400" itemid4="61513500" />
    <SETITEM id="61513600" name="시그넘 가죽 세트" itemid1="61513600" itemid2="61513700" itemid3="61513800" itemid4="61513900" itemid5="61514000" />
    <SETITEM id="61514100" name="시그넘 사슬 세트" itemid1="61514100" itemid2="61514200" itemid3="61514300" itemid4="61514400" itemid5="61514500" />
    <SETITEM id="61514600" name="시그넘 판금 세트" itemid1="61514600" itemid2="61514700" itemid3="61514800" itemid4="61514900" itemid5="61515000" />
    <SETITEM id="61523100" name="원소 세트" itemid1="61523100" itemid2="61523200" itemid3="61523400" itemid4="61523500" />
    <SETITEM id="61523600" name="어두운 숲 세트" itemid1="61523600" itemid2="61523700" itemid3="61523800" itemid4="61523900" itemid5="61524000" />
    <SETITEM id="61524100" name="레이븐 사슬 세트" itemid1="61524100" itemid2="61524200" itemid3="61524300" itemid4="61524400" itemid5="61524500" />
    <SETITEM id="61524600" name="장인의 판금 세트" itemid1="61524600" itemid2="61524700" itemid3="61524800" itemid4="61524900" itemid5="61525000" />
    <SETITEM id="61633100" name="플뢰르 드 리스 세트" itemid1="61633100" itemid2="61633200" itemid3="61633400" itemid4="61633500" buffid2="6000080" buffid3="6000081" buffid4="6000082" />
    <SETITEM id="61633600" name="집행자의 가죽 세트" itemid1="61633600" itemid2="61633700" itemid3="61633800" itemid4="61633900" itemid5="61634000" buffid2="6000090" buffid3="6000091" buffid4="6000092" buffid5="6000093" />
    <SETITEM id="61634100" name="기병대 세트" itemid1="61634100" itemid2="61634200" itemid3="61634300" itemid4="61634400" itemid5="61634500" buffid2="6000100" buffid3="6000101" buffid4="6000102" buffid5="6000103" />
    <SETITEM id="61634600" name="영웅의 판금 세트" itemid1="61634600" itemid2="61634700" itemid3="61634800" itemid4="61634900" itemid5="61635000" buffid2="6000110" buffid3="6000111" buffid4="6000112" buffid5="6000113" />
    <SETITEM id="61623100" name="암흑 사제 세트" itemid1="61623100" itemid2="61623200" itemid3="61623400" itemid4="61623500" />
    <SETITEM id="61623600" name="검은 의식 세트" itemid1="61623600" itemid2="61623700" itemid3="61623800" itemid4="61623900" itemid5="61624000" />
    <SETITEM id="61624100" name="불한당 세트" itemid1="61624100" itemid2="61624200" itemid3="61624300" itemid4="61624400" itemid5="61624500" />
    <SETITEM id="61624600" name="유령기사의 판금 세트" itemid1="61624600" itemid2="61624700" itemid3="61624800" itemid4="61624900" itemid5="61625000" />
    <SETITEM id="61733100" name="시온 수도사 세트" itemid1="61733100" itemid2="61733200" itemid3="61733400" itemid4="61733500" buffid2="6000120" buffid3="6000121" buffid4="6000122" />
    <SETITEM id="61733600" name="결사단 세트" itemid1="61733600" itemid2="61733700" itemid3="61733800" itemid4="61733900" itemid5="61734000" buffid2="6000130" buffid3="6000131" buffid4="6000132" buffid5="6000133" />
    <SETITEM id="61734100" name="사령 세트" itemid1="61734100" itemid2="61734200" itemid3="61734300" itemid4="61734400" itemid5="61734500" buffid2="6000140" buffid3="6000141" buffid4="6000142" buffid5="6000143" />
    <SETITEM id="61734600" name="리비우트의 판금 세트" itemid1="61734600" itemid2="61734700" itemid3="61734800" itemid4="61734900" itemid5="61735000" buffid2="6000150" buffid3="6000151" buffid4="6000152" buffid5="6000153" />
    <SETITEM id="62013100" name="리지드 천 세트" itemid1="62013100" itemid2="62013200" itemid3="62013400" itemid4="62013500" />
    <SETITEM id="62013600" name="리지드 가죽 세트" itemid1="62013600" itemid2="62013700" itemid3="62013800" itemid4="62013900" itemid5="62014000" />
    <SETITEM id="62014100" name="리지드 사슬 세트" itemid1="62014100" itemid2="62014200" itemid3="62014300" itemid4="62014400" itemid5="62014500" />
    <SETITEM id="62014600" name="리지드 판금 세트" itemid1="62014600" itemid2="62014700" itemid3="62014800" itemid4="62014900" itemid5="62015000" />
    <SETITEM id="62023100" name="제례용 예복 세트" itemid1="62023100" itemid2="62023200" itemid3="62023400" itemid4="62023500" />
    <SETITEM id="62023600" name="퀼리안 가죽 세트" itemid1="62023600" itemid2="62023700" itemid3="62023800" itemid4="62023900" itemid5="62024000" />
    <SETITEM id="62024100" name="상급 용병 세트" itemid1="62024100" itemid2="62024200" itemid3="62024300" itemid4="62024400" itemid5="62024500" />
    <SETITEM id="62024600" name="헌신의 판금 세트" itemid1="62024600" itemid2="62024700" itemid3="62024800" itemid4="62024900" itemid5="62025000" />
    <SETITEM id="62133100" name="매혹 세트" itemid1="62133100" itemid2="62133200" itemid3="62133400" itemid4="62133500" buffid2="6000160" buffid3="6000161" buffid4="6000162" />
    <SETITEM id="62133600" name="겨울 가죽 세트" itemid1="62133600" itemid2="62133700" itemid3="62133800" itemid4="62133900" itemid5="62134000" buffid2="6000170" buffid3="6000171" buffid4="6000172" buffid5="6000173" />
    <SETITEM id="62134100" name="산악수비대 세트" itemid1="62134100" itemid2="62134200" itemid3="62134300" itemid4="62134400" itemid5="62134500" buffid2="6000180" buffid3="6000181" buffid4="6000182" buffid5="6000183" />
    <SETITEM id="62134600" name="용기병의 판금 세트" itemid1="62134600" itemid2="62134700" itemid3="62134800" itemid4="62134900" itemid5="62135000" buffid2="6000190" buffid3="6000191" buffid4="6000192" buffid5="6000193" />
    <SETITEM id="62233100" name="광기의 눈 부족 영웅 천 세트" itemid1="62233100" itemid2="62233200" itemid3="62233300" itemid4="62233400" itemid5="62233500" buffid2="6000200" buffid3="6000201" buffid4="6000202" buffid5="6000203" />
    <SETITEM id="62233600" name="광기의 눈 부족 영웅 가죽 세트" itemid1="62233600" itemid2="62233700" itemid3="62233800" itemid4="62233900" itemid5="62234000" buffid2="6000210" buffid3="6000211" buffid4="6000212" buffid5="6000213" />
    <SETITEM id="62234100" name="광기의 눈 부족 영웅 사슬 세트" itemid1="62234100" itemid2="62234200" itemid3="62234300" itemid4="62234400" itemid5="62234500" buffid2="6000220" buffid3="6000221" buffid4="6000222" buffid5="6000223" />
    <SETITEM id="62234600" name="광기의 눈 부족 영웅 판금 세트" itemid1="62234600" itemid2="62234700" itemid3="62234800" itemid4="62234900" itemid5="62235000" buffid2="6000230" buffid3="6000231" buffid4="6000232" buffid5="6000233" />
    <SETITEM id="62233101" name="흰색 예티 부족 영웅 천 세트" itemid1="62233101" itemid2="62233201" itemid3="62233301" itemid4="62233401" itemid5="62233501" buffid2="6000240" buffid3="6000241" buffid4="6000242" buffid5="6000243" />
    <SETITEM id="62233601" name="흰색 예티 부족 영웅 가죽 세트" itemid1="62233601" itemid2="62233701" itemid3="62233801" itemid4="62233901" itemid5="62234001" buffid2="6000250" buffid3="6000251" buffid4="6000252" buffid5="6000253" />
    <SETITEM id="62234101" name="흰색 예티 부족 영웅 사슬 세트" itemid1="62234101" itemid2="62234201" itemid3="62234301" itemid4="62234401" itemid5="62234501" buffid2="6000260" buffid3="6000261" buffid4="6000262" buffid5="6000263" />
    <SETITEM id="62234601" name="흰색 예티 부족 영웅 판금 세트" itemid1="62234601" itemid2="62234701" itemid3="62234801" itemid4="62234901" itemid5="62235001" buffid2="6000270" buffid3="6000271" buffid4="6000272" buffid5="6000273" />
    <SETITEM id="62413100" name="옵티움 천 세트" itemid1="62413100" itemid2="62413200" itemid3="62413400" itemid4="62413500" />
    <SETITEM id="62413600" name="옵티움 가죽 세트" itemid1="62413600" itemid2="62413700" itemid3="62413800" itemid4="62413900" itemid5="62414000" />
    <SETITEM id="62414100" name="옵티움 사슬 세트" itemid1="62414100" itemid2="62414200" itemid3="62414300" itemid4="62414400" itemid5="62414500" />
    <SETITEM id="62414600" name="옵티움 판금 세트" itemid1="62414600" itemid2="62414700" itemid3="62414800" itemid4="62414900" itemid5="62415000" />
    <SETITEM id="62523100" name="엘스테어 세트" itemid1="62523100" itemid2="62523200" itemid3="62523400" itemid4="62523500" />
    <SETITEM id="62523600" name="사수 세트" itemid1="62523600" itemid2="62523700" itemid3="62523800" itemid4="62523900" itemid5="62524000" />
    <SETITEM id="62524100" name="유랑용병 세트" itemid1="62524100" itemid2="62524200" itemid3="62524300" itemid4="62524400" itemid5="62524500" />
    <SETITEM id="62524600" name="센티스 판금 세트" itemid1="62524600" itemid2="62524700" itemid3="62524800" itemid4="62524900" itemid5="62525000" />
    <SETITEM id="62713100" name="매그너스 천 세트" itemid1="62713100" itemid2="62713200" itemid3="62713400" itemid4="62713500" />
    <SETITEM id="62713600" name="매그너스 가죽 세트" itemid1="62713600" itemid2="62713700" itemid3="62713800" itemid4="62713900" itemid5="62714000" />
    <SETITEM id="62714100" name="매그너스 사슬 세트" itemid1="62714100" itemid2="62714200" itemid3="62714300" itemid4="62714400" itemid5="62714500" />
    <SETITEM id="62714600" name="매그너스 판금 세트" itemid1="62714600" itemid2="62714700" itemid3="62714800" itemid4="62714900" itemid5="62715000" />
    <SETITEM id="62823100" name="치유사 세트" itemid1="62823100" itemid2="62823200" itemid3="62823300" itemid4="62823400" itemid5="62823500" />
    <SETITEM id="62823600" name="순찰자 세트" itemid1="62823600" itemid2="62823700" itemid3="62823800" itemid4="62823900" itemid5="62824000" />
    <SETITEM id="62824100" name="항쟁 세트" itemid1="62824100" itemid2="62824200" itemid3="62824300" itemid4="62824400" itemid5="62824500" />
    <SETITEM id="62824600" name="수호자 세트" itemid1="62824600" itemid2="62824700" itemid3="62824800" itemid4="62824900" itemid5="62825000" />
    <SETITEM id="62933100" name="신앙 세트" itemid1="62933100" itemid2="62933200" itemid3="62933400" itemid4="62933500" buffid2="6000280" buffid3="6000281" buffid4="6000282" />
    <SETITEM id="62933600" name="안개술사 세트" itemid1="62933600" itemid2="62933700" itemid3="62933900" itemid4="62934000" buffid2="6000290" buffid3="6000291" buffid4="6000292" />
    <SETITEM id="62934100" name="아퀼라 세트" itemid1="62934100" itemid2="62934200" itemid3="62934300" itemid4="62934400" itemid5="62934500" buffid2="6000300" buffid3="6000301" buffid4="6000302" buffid5="6000303" />
    <SETITEM id="62934600" name="호수의 기사 세트" itemid1="62934600" itemid2="62934700" itemid3="62934800" itemid4="62934900" itemid5="62935000" buffid2="6000310" buffid3="6000311" buffid4="6000312" buffid5="6000313" />
    <SETITEM id="63013100" name="프리무스 천 세트" itemid1="63013100" itemid2="63013200" itemid3="63013400" itemid4="63013500" />
    <SETITEM id="63013600" name="프리무스 가죽 세트" itemid1="63013600" itemid2="63013700" itemid3="63013800" itemid4="63013900" itemid5="63014000" />
    <SETITEM id="63014100" name="프리무스 사슬 세트" itemid1="63014100" itemid2="63014200" itemid3="63014300" itemid4="63014400" itemid5="63014500" />
    <SETITEM id="63014600" name="프리무스 판금 세트" itemid1="63014600" itemid2="63014700" itemid3="63014800" itemid4="63014900" itemid5="63015000" />
    <SETITEM id="63123100" name="렌델 제복 세트" itemid1="63123100" itemid2="63123200" itemid3="63123300" itemid4="63123400" itemid5="63123500" />
    <SETITEM id="63123600" name="만월의 가죽 세트" itemid1="63123600" itemid2="63123700" itemid3="63123800" itemid4="63123900" itemid5="63124000" />
    <SETITEM id="63124100" name="청부업자 세트" itemid1="63124100" itemid2="63124200" itemid3="63124300" itemid4="63124400" itemid5="63124500" />
    <SETITEM id="63124600" name="투쟁의 판금 세트" itemid1="63124600" itemid2="63124700" itemid3="63124800" itemid4="63124900" itemid5="63125000" />
    <SETITEM id="63233100" name="귀족 세트" itemid1="63233100" itemid2="63233200" itemid3="63233400" itemid4="63233500" buffid2="6000320" buffid3="6000321" buffid4="6000322" />
    <SETITEM id="63233600" name="도적의 가죽 세트" itemid1="63233600" itemid2="63233700" itemid3="63233800" itemid4="63233900" itemid5="63234000" buffid2="6000330" buffid3="6000331" buffid4="6000332" buffid5="6000333" />
    <SETITEM id="63234100" name="이국 세트" itemid1="63234100" itemid2="63234200" itemid3="63234300" itemid4="63234400" itemid5="63234500" buffid2="6000340" buffid3="6000341" buffid4="6000342" buffid5="6000343" />
    <SETITEM id="63234600" name="통곡의 판금 세트" itemid1="63234600" itemid2="63234700" itemid3="63234800" itemid4="63234900" itemid5="63235000" buffid2="6000350" buffid3="6000351" buffid4="6000352" buffid5="6000353" />
    <SETITEM id="63543100" name="투지의 천 세트" itemid1="63543100" itemid2="63543200" itemid3="63543400" itemid4="63543500" buffid2="6000360" buffid3="6000361" buffid4="6000362" />
    <SETITEM id="63543600" name="투지의 가죽 세트" itemid1="63543600" itemid2="63543700" itemid3="63543800" itemid4="63543900" itemid5="63544000" buffid2="6000370" buffid3="6000371" buffid4="6000372" buffid5="6000373" />
    <SETITEM id="63544100" name="투지의 사슬 세트" itemid1="63544100" itemid2="63544200" itemid3="63544300" itemid4="63544400" itemid5="63544500" buffid2="6000380" buffid3="6000381" buffid4="6000382" buffid5="6000383" />
    <SETITEM id="63544600" name="투지의 판금 세트" itemid1="63544600" itemid2="63544700" itemid3="63544800" itemid4="63544900" itemid5="63545000" buffid2="6000390" buffid3="6000391" buffid4="6000392" buffid5="6000393" />
    <SETITEM id="63543101" name="케찰의 천 세트" itemid1="63543101" itemid2="63543201" itemid3="63543401" itemid4="63543501" buffid2="6000400" buffid3="6000401" buffid4="6000402" />
    <SETITEM id="63543601" name="케찰의 가죽 세트" itemid1="63543601" itemid2="63543701" itemid3="63543801" itemid4="63543901" itemid5="63544001" buffid2="6000410" buffid3="6000411" buffid4="6000412" buffid5="6000413" />
    <SETITEM id="63544101" name="케찰의 사슬 세트" itemid1="63544101" itemid2="63544201" itemid3="63544301" itemid4="63544401" itemid5="63544501" buffid2="6000420" buffid3="6000421" buffid4="6000422" buffid5="6000423" />
    <SETITEM id="63544601" name="케찰의 판금 세트" itemid1="63544601" itemid2="63544701" itemid3="63544801" itemid4="63544901" itemid5="63545001" buffid2="6000430" buffid3="6000431" buffid4="6000432" buffid5="6000433" />
    <SETITEM id="63543102" name="주교 세트" itemid1="63543102" itemid2="63543202" itemid3="63543402" itemid4="63543502" buffid2="6000440" buffid3="6000441" buffid4="6000442" />
    <SETITEM id="63543602" name="붉은 수도사 세트" itemid1="63543602" itemid2="63543702" itemid3="63543802" itemid4="63543902" itemid5="63544002" buffid2="6000450" buffid3="6000451" buffid4="6000452" buffid5="6000453" />
    <SETITEM id="63544102" name="성투사 세트" itemid1="63544102" itemid2="63544202" itemid3="63544302" itemid4="63544402" itemid5="63544502" buffid2="6000460" buffid3="6000461" buffid4="6000462" buffid5="6000463" />
    <SETITEM id="63544602" name="성기사의 판금 세트" itemid1="63544602" itemid2="63544702" itemid3="63544802" itemid4="63544902" itemid5="63545002" buffid2="6000470" buffid3="6000471" buffid4="6000472" buffid5="6000473" />
    <SETITEM id="64047300" name="웅장한 심판의 장신구 세트" itemid1="64047300" itemid2="64047301" itemid3="64047100" buffid2="6000720" buffid3="6000721" />
    <SETITEM id="64047302" name="화려한 심판의 장신구 세트" itemid1="64047302" itemid2="64047303" itemid3="64047101" buffid2="6000722" buffid3="6000723" />
    <SETITEM id="64047304" name="강인한 심판의 장신구 세트" itemid1="64047304" itemid2="64047305" itemid3="64047102" buffid2="6000724" buffid3="6000725" />
    <SETITEM id="64047306" name="웅장한 초월자 장신구 세트" itemid1="64047306" itemid2="64047307" itemid3="64047103" buffid2="6000730" buffid3="6000731" />
    <SETITEM id="64047308" name="화려한 초월자 장신구 세트" itemid1="64047308" itemid2="64047309" itemid3="64047104" buffid2="6000732" buffid3="6000733" />
    <SETITEM id="64047310" name="강인한 초월자 장신구 세트" itemid1="64047310" itemid2="64047311" itemid3="64047105" buffid2="6000734" buffid3="6000735" />
    <SETITEM id="64047330" name="웅장한 리온 장신구 세트" itemid1="64047330" itemid2="64047331" itemid3="64047125" buffid2="6000740" buffid3="6000741" />
    <SETITEM id="64047332" name="화려한 리온 장신구 세트" itemid1="64047332" itemid2="64047333" itemid3="64047126" buffid2="6000742" buffid3="6000743" />
    <SETITEM id="64047334" name="강인한 리온 장신구 세트" itemid1="64047334" itemid2="64047335" itemid3="64047127" buffid2="6000744" buffid3="6000745" />
    <SETITEM id="63833100" name="검은 늪의 천 세트" itemid1="63833100" itemid2="63833200" itemid3="63833400" itemid4="63833500" buffid2="6000780" buffid3="6000781" buffid4="6000782" />
    <SETITEM id="63833600" name="검은 늪의 가죽 세트" itemid1="63833600" itemid2="63833700" itemid3="63833800" itemid4="63833900" itemid5="63834000" buffid2="6000790" buffid3="6000791" buffid4="6000792" buffid5="6000793" />
    <SETITEM id="63834100" name="검은 늪의 사슬 세트" itemid1="63834100" itemid2="63834200" itemid3="63834300" itemid4="63834400" itemid5="63834500" buffid2="6000801" buffid3="6000802" buffid4="6000803" buffid5="6000804" />
    <SETITEM id="63834600" name="검은 늪의 판금 세트" itemid1="63834600" itemid2="63834700" itemid3="63834800" itemid4="63834900" itemid5="63835000" buffid2="6000812" buffid3="6000813" buffid4="6000814" buffid5="6000815" />
    <SETITEM id="64033101" name="견고한 여신의 천 세트" itemid1="64033101" itemid2="64033201" itemid3="64033401" itemid4="64033501" buffid2="6000820" buffid3="6000821" buffid4="6000822" />
    <SETITEM id="64033601" name="견고한 여신의 가죽 세트" itemid1="64033601" itemid2="64033701" itemid3="64033801" itemid4="64033901" itemid5="64034001" buffid2="6000830" buffid3="6000831" buffid4="6000832" buffid5="6000833" />
    <SETITEM id="64034101" name="견고한 여신의 비늘 세트" itemid1="64034101" itemid2="64034201" itemid3="64034301" itemid4="64034401" itemid5="64034501" buffid2="6000841" buffid3="6000842" buffid4="6000843" buffid5="6000844" />
    <SETITEM id="64034601" name="견고한 여신의 판금 세트" itemid1="64034601" itemid2="64034701" itemid3="64034801" itemid4="64034901" itemid5="64035001" buffid2="6000852" buffid3="6000853" buffid4="6000854" buffid5="6000855" />
    <SETITEM id="64033102" name="초월적인 여신의 천 세트" itemid1="64033102" itemid2="64033202" itemid3="64033402" itemid4="64033502" buffid2="6000860" buffid3="6000861" buffid4="6000862" />
    <SETITEM id="64033602" name="초월적인 여신의 가죽 세트" itemid1="64033602" itemid2="64033702" itemid3="64033802" itemid4="64033902" itemid5="64034002" buffid2="6000870" buffid3="6000871" buffid4="6000872" buffid5="6000873" />
    <SETITEM id="64034102" name="초월적인 여신의 비늘 세트" itemid1="64034102" itemid2="64034202" itemid3="64034302" itemid4="64034402" itemid5="64034502" buffid2="6000881" buffid3="6000882" buffid4="6000883" buffid5="6000884" />
    <SETITEM id="64034602" name="초월적인 여신의 판금 세트" itemid1="64034602" itemid2="64034702" itemid3="64034802" itemid4="64034902" itemid5="64035002" buffid2="6000892" buffid3="6000893" buffid4="6000894" buffid5="6000895" />
    <SETITEM id="64033103" name="날렵한 여신의 천 세트" itemid1="64033103" itemid2="64033203" itemid3="64033403" itemid4="64033503" buffid2="6000900" buffid3="6000901" buffid4="6000902" />
    <SETITEM id="64033603" name="날렵한 여신의 가죽 세트" itemid1="64033603" itemid2="64033703" itemid3="64033803" itemid4="64033903" itemid5="64034003" buffid2="6000910" buffid3="6000911" buffid4="6000912" buffid5="6000913" />
    <SETITEM id="64034103" name="날렵한 여신의 비늘 세트" itemid1="64034103" itemid2="64034203" itemid3="64034303" itemid4="64034403" itemid5="64034503" buffid2="6000921" buffid3="6000922" buffid4="6000923" buffid5="6000924" />
    <SETITEM id="64034603" name="날렵한 여신의 판금 세트" itemid1="64034603" itemid2="64034703" itemid3="64034803" itemid4="64034903" itemid5="64035003" buffid2="6000932" buffid3="6000933" buffid4="6000934" buffid5="6000935" />
    <SETITEM id="64033104" name="활력적인 여신의 천 세트" itemid1="64033104" itemid2="64033204" itemid3="64033404" itemid4="64033504" buffid2="6000940" buffid3="6000941" buffid4="6000942" />
    <SETITEM id="64033604" name="활력적인 여신의 가죽 세트" itemid1="64033604" itemid2="64033704" itemid3="64033804" itemid4="64033904" itemid5="64034004" buffid2="6000950" buffid3="6000951" buffid4="6000952" buffid5="6000953" />
    <SETITEM id="64034104" name="활력적인 여신의 비늘 세트" itemid1="64034104" itemid2="64034204" itemid3="64034304" itemid4="64034404" itemid5="64034504" buffid2="6000961" buffid3="6000962" buffid4="6000963" buffid5="6000964" />
    <SETITEM id="64034604" name="활력적인 여신의 판금 세트" itemid1="64034604" itemid2="64034704" itemid3="64034804" itemid4="64034904" itemid5="64035004" buffid2="6000972" buffid3="6000973" buffid4="6000974" buffid5="6000975" />
    <SETITEM id="64043100" name="레나스 보호 천 세트" itemid1="64043100" itemid2="64043200" itemid3="64043400" itemid4="64043500" buffid2="6001260" buffid3="6001261" buffid4="6001262" />
    <SETITEM id="64043600" name="레나스 보호 가죽 세트" itemid1="64043600" itemid2="64043700" itemid3="64043900" itemid4="64044000" buffid2="6001270" buffid3="6001271" buffid4="6001272" />
    <SETITEM id="64044100" name="레나스 보호 비늘 세트" itemid1="64044100" itemid2="64044200" itemid3="64044300" itemid4="64044400" itemid5="64044500" buffid2="6001281" buffid3="6001282" buffid4="6001283" buffid5="6001284" />
    <SETITEM id="64044600" name="레나스 보호 판금 세트" itemid1="64044600" itemid2="64044700" itemid3="64044800" itemid4="64044900" itemid5="64045000" buffid2="6001292" buffid3="6001293" buffid4="6001294" buffid5="6001295" />
    <SETITEM id="64043101" name="레나스 손길 천 세트" itemid1="64043101" itemid2="64043201" itemid3="64043401" itemid4="64043501" buffid2="6001300" buffid3="6001301" buffid4="6001302" />
    <SETITEM id="64043601" name="레나스 손길 가죽 세트" itemid1="64043601" itemid2="64043701" itemid3="64043901" itemid4="64044001" buffid2="6001310" buffid3="6001311" buffid4="6001312" />
    <SETITEM id="64044101" name="레나스 손길 비늘 세트" itemid1="64044101" itemid2="64044201" itemid3="64044301" itemid4="64044401" itemid5="64044501" buffid2="6001321" buffid3="6001322" buffid4="6001323" buffid5="6001324" />
    <SETITEM id="64044601" name="레나스 손길 판금 세트" itemid1="64044601" itemid2="64044701" itemid3="64044801" itemid4="64044901" itemid5="64045001" buffid2="6001332" buffid3="6001333" buffid4="6001334" buffid5="6001335" />
    <SETITEM id="64043102" name="레나스 강림 천 세트" itemid1="64043102" itemid2="64043202" itemid3="64043402" itemid4="64043502" buffid2="6001340" buffid3="6001341" buffid4="6001342" />
    <SETITEM id="64043602" name="레나스 강림 가죽 세트" itemid1="64043602" itemid2="64043702" itemid3="64043902" itemid4="64044002" buffid2="6001350" buffid3="6001351" buffid4="6001352" />
    <SETITEM id="64044102" name="레나스 강림 비늘 세트" itemid1="64044102" itemid2="64044202" itemid3="64044302" itemid4="64044402" itemid5="64044502" buffid2="6001360" buffid3="6001361" buffid4="6001362" buffid5="6001363" />
    <SETITEM id="64044602" name="레나스 강림 판금 세트" itemid1="64044602" itemid2="64044702" itemid3="64044802" itemid4="64044902" itemid5="64045002" buffid2="6001370" buffid3="6001371" buffid4="6001372" buffid5="6001373" />
    <SETITEM id="64043103" name="레나스 현신 천 세트" itemid1="64043103" itemid2="64043203" itemid3="64043403" itemid4="64043503" buffid2="6001345" buffid3="6001346" buffid4="6001347" />
    <SETITEM id="64043603" name="레나스 현신 가죽 세트" itemid1="64043603" itemid2="64043703" itemid3="64043903" itemid4="64044003" buffid2="6001355" buffid3="6001356" buffid4="6001357" />
    <SETITEM id="64044103" name="레나스 현신 사슬 세트" itemid1="64044103" itemid2="64044203" itemid3="64044303" itemid4="64044403" itemid5="64044503" buffid2="6001365" buffid3="6001366" buffid4="6001367" buffid5="6001368" />
    <SETITEM id="64044603" name="레나스 현신 판금 세트" itemid1="64044603" itemid2="64044703" itemid3="64044803" itemid4="64044903" itemid5="64045003" buffid2="6001375" buffid3="6001376" buffid4="6001377" buffid5="6001378" />
    <SETITEM id="1800280" name="지옥전사 장신구 세트" itemid1="1800280" itemid2="1800281" itemid3="1800282" buffid2="6001460" buffid3="6001461" />
    <SETITEM id="1800283" name="지옥마법사 장신구 세트" itemid1="1800283" itemid2="1800284" itemid3="1800285" buffid2="6001470" buffid3="6001471" />
    <SETITEM id="1800284" name="지옥암살자 장신구 세트" itemid1="1800286" itemid2="1800287" itemid3="1800288" buffid2="6001472" buffid3="6001473" />
    <SETITEM id="63837332" name="견고한 진홍의 장신구 세트" itemid1="63837332" itemid2="63837340" itemid3="63837116" buffid2="6001480" buffid3="6001481" />
    <SETITEM id="63837333" name="초월적인 진홍의 장신구 세트" itemid1="63837333" itemid2="63837341" itemid3="63837117" buffid2="6001490" buffid3="6001491" />
    <SETITEM id="63837334" name="날렵한 진홍의 장신구 세트" itemid1="63837334" itemid2="63837342" itemid3="63837118" buffid2="6001500" buffid3="6001501" />
    <SETITEM id="63837335" name="찬란한 진홍의 장신구 세트" itemid1="63837335" itemid2="63837343" itemid3="63837119" buffid2="6001510" buffid3="6001511" />
    <SETITEM id="63837336" name="숭고한 진홍의 장신구 세트" itemid1="63837336" itemid2="63837344" itemid3="63837120" buffid2="6001520" buffid3="6001521" />
    <SETITEM id="63837337" name="몽환적인 진홍의 장신구 세트" itemid1="63837337" itemid2="63837345" itemid3="63837121" buffid2="6001530" buffid3="6001531" />
    <SETITEM id="63837338" name="확고한 진홍의 장신구 세트" itemid1="63837338" itemid2="63837346" itemid3="63837122" buffid2="6001540" buffid3="6001541" />
    <SETITEM id="63837339" name="날카로운 진홍의 장신구 세트" itemid1="63837339" itemid2="63837347" itemid3="63837123" buffid2="6001550" buffid3="6001551" />
    <SETITEM id="1800394" name="정열의 장신구 세트" itemid1="1800394" itemid2="1800398" buffid2="6001560" />
    <SETITEM id="1800395" name="냉기의 장신구 세트" itemid1="1800395" itemid2="1800399" buffid2="6001561" />
    <SETITEM id="1800396" name="대기의 장신구 세트" itemid1="1800396" itemid2="1800404" buffid2="6001562" />
    <SETITEM id="1800397" name="창공의 장신구 세트" itemid1="1800397" itemid2="1800405" buffid2="6001563" />
</maiet>
